bidsapp_helper/__init__.py
bidsapp_helper/descriptor.py
bidsapp_helper/parser.py
bidsapp_helper-0.1.0.dist-info/METADATA
bidsapp_helper-0.1.0.dist-info/WHEEL
bidsapp_helper-0.1.0.dist-info/entry_points.txt
bidsapp_helper-0.1.0.dist-info/licenses/LICENSE
bidsapp_helper-0.1.0.dist-info/RECORD
