Metadata-Version: 2.3
Name: bidsapp-helper
Version: 0.1.0
Summary: Python helper package to simplify creation of BIDS apps
Project-URL: Repository, https://github.com/kaitj/bidsapp-helper
Author-email: Jason Kai <jason.kai@childmind.org>
License-Expression: MIT
License-File: LICENSE
Keywords: argparse,bids,neuroimaging
Classifier: Development Status :: 3 - Alpha
Classifier: Intended Audience :: Science/Research
Classifier: License :: OSI Approved :: MIT License
Classifier: Programming Language :: Python :: 3
Classifier: Programming Language :: Python :: 3.11
Classifier: Programming Language :: Python :: 3.12
Classifier: Topic :: Scientific/Engineering
Classifier: Topic :: Software Development :: Libraries :: Python Modules
Requires-Python: >=3.11
Requires-Dist: pyyaml>=6.0.2
